<?xml version="1.0" encoding="UTF-8"?>
<MetaDataObject xmlns="http://v8.1c.ru/8.3/MDClasses" xmlns:app="http://v8.1c.ru/8.2/managed-application/core" xmlns:cfg="http://v8.1c.ru/8.1/data/enterprise/current-config" xmlns:cmi="http://v8.1c.ru/8.2/managed-application/cmi" xmlns:ent="http://v8.1c.ru/8.1/data/enterprise" xmlns:lf="http://v8.1c.ru/8.2/managed-application/logform" xmlns:style="http://v8.1c.ru/8.1/data/ui/style" xmlns:sys="http://v8.1c.ru/8.1/data/ui/fonts/system" xmlns:v8="http://v8.1c.ru/8.1/data/core" xmlns:v8ui="http://v8.1c.ru/8.1/data/ui" xmlns:web="http://v8.1c.ru/8.1/data/ui/colors/web" xmlns:win="http://v8.1c.ru/8.1/data/ui/colors/windows" xmlns:xen="http://v8.1c.ru/8.3/xcf/enums" xmlns:xpr="http://v8.1c.ru/8.3/xcf/predef" xmlns:xr="http://v8.1c.ru/8.3/xcf/readable" xmlns:xs="http://www.w3.org/2001/XMLSchema" xmlns:xsi="http://www.w3.org/2001/XMLSchema-instance">
	<InformationRegister uuid="acf424d5-0f88-4635-bb05-31c1a8b2d9ac">
		<InternalInfo>
			<xr:GeneratedType name="InformationRegisterRecord.ЦеныНоменклатурыЗакупочные" category="Record">
				<xr:TypeId>bbf306f6-9944-4f05-9ea2-1f4a53422886</xr:TypeId>
				<xr:ValueId>ccadb36b-a163-4765-933d-d0e03f773bd1</xr:ValueId>
			</xr:GeneratedType>
			<xr:GeneratedType name="InformationRegisterManager.ЦеныНоменклатурыЗакупочные" category="Manager">
				<xr:TypeId>e087380c-808d-40a0-826e-d0c55f1f7845</xr:TypeId>
				<xr:ValueId>5d03badf-6d77-4b59-86a7-98a250b46d59</xr:ValueId>
			</xr:GeneratedType>
			<xr:GeneratedType name="InformationRegisterSelection.ЦеныНоменклатурыЗакупочные" category="Selection">
				<xr:TypeId>e0402152-0959-4758-b9bc-20e33e1f4919</xr:TypeId>
				<xr:ValueId>8629bc07-fce6-4e16-9c76-15ae8acee17a</xr:ValueId>
			</xr:GeneratedType>
			<xr:GeneratedType name="InformationRegisterList.ЦеныНоменклатурыЗакупочные" category="List">
				<xr:TypeId>bed469bb-2ec1-40b4-a153-c03c165f629c</xr:TypeId>
				<xr:ValueId>2f5c933a-9ff9-4621-aeab-7f18da6aae71</xr:ValueId>
			</xr:GeneratedType>
			<xr:GeneratedType name="InformationRegisterRecordSet.ЦеныНоменклатурыЗакупочные" category="RecordSet">
				<xr:TypeId>fb188825-917d-42ba-a5a3-fe24ec2439f2</xr:TypeId>
				<xr:ValueId>742c3723-1218-49a2-bde4-d5bf7378e4ea</xr:ValueId>
			</xr:GeneratedType>
			<xr:GeneratedType name="InformationRegisterRecordKey.ЦеныНоменклатурыЗакупочные" category="RecordKey">
				<xr:TypeId>8c079c7a-e82a-4f31-99ac-e4fcf3a1c452</xr:TypeId>
				<xr:ValueId>42859607-7832-4462-a7d6-cb528246f158</xr:ValueId>
			</xr:GeneratedType>
			<xr:GeneratedType name="InformationRegisterRecordManager.ЦеныНоменклатурыЗакупочные" category="RecordManager">
				<xr:TypeId>6cbb06a8-62d4-4195-9ecb-2cf46a502d97</xr:TypeId>
				<xr:ValueId>9888e395-fcc7-4a83-95f6-22ea0ec7639e</xr:ValueId>
			</xr:GeneratedType>
		</InternalInfo>
		<Properties>
			<Name>ЦеныНоменклатурыЗакупочные</Name>
			<Synonym>
				<v8:item>
					<v8:lang>ru</v8:lang>
					<v8:content>Цены номенклатуры закупочные</v8:content>
				</v8:item>
				<v8:item>
					<v8:lang>en</v8:lang>
					<v8:content>Prices of nomenclature</v8:content>
				</v8:item>
			</Synonym>
			<Comment/>
			<UseStandardCommands>true</UseStandardCommands>
			<EditType>InList</EditType>
			<DefaultRecordForm/>
			<DefaultListForm>InformationRegister.ЦеныНоменклатурыЗакупочные.Form.ФормаСписка</DefaultListForm>
			<AuxiliaryRecordForm/>
			<AuxiliaryListForm/>
			<StandardAttributes>
				<xr:StandardAttribute name="Active">
					<xr:LinkByType/>
					<xr:FillChecking>DontCheck</xr:FillChecking>
					<xr:MultiLine>false</xr:MultiLine>
					<xr:FillFromFillingValue>false</xr:FillFromFillingValue>
					<xr:CreateOnInput>Auto</xr:CreateOnInput>
					<xr:MaxValue xsi:nil="true"/>
					<xr:ToolTip/>
					<xr:ExtendedEdit>false</xr:ExtendedEdit>
					<xr:Format/>
					<xr:ChoiceForm/>
					<xr:QuickChoice>Auto</xr:QuickChoice>
					<xr:ChoiceHistoryOnInput>Auto</xr:ChoiceHistoryOnInput>
					<xr:EditFormat/>
					<xr:PasswordMode>false</xr:PasswordMode>
					<xr:MarkNegatives>false</xr:MarkNegatives>
					<xr:MinValue xsi:nil="true"/>
					<xr:Synonym/>
					<xr:Comment/>
					<xr:FullTextSearch>Use</xr:FullTextSearch>
					<xr:ChoiceParameterLinks/>
					<xr:FillValue xsi:nil="true"/>
					<xr:Mask/>
					<xr:ChoiceParameters/>
				</xr:StandardAttribute>
				<xr:StandardAttribute name="LineNumber">
					<xr:LinkByType/>
					<xr:FillChecking>DontCheck</xr:FillChecking>
					<xr:MultiLine>false</xr:MultiLine>
					<xr:FillFromFillingValue>false</xr:FillFromFillingValue>
					<xr:CreateOnInput>Auto</xr:CreateOnInput>
					<xr:MaxValue xsi:nil="true"/>
					<xr:ToolTip/>
					<xr:ExtendedEdit>false</xr:ExtendedEdit>
					<xr:Format/>
					<xr:ChoiceForm/>
					<xr:QuickChoice>Auto</xr:QuickChoice>
					<xr:ChoiceHistoryOnInput>Auto</xr:ChoiceHistoryOnInput>
					<xr:EditFormat/>
					<xr:PasswordMode>false</xr:PasswordMode>
					<xr:MarkNegatives>false</xr:MarkNegatives>
					<xr:MinValue xsi:nil="true"/>
					<xr:Synonym/>
					<xr:Comment/>
					<xr:FullTextSearch>Use</xr:FullTextSearch>
					<xr:ChoiceParameterLinks/>
					<xr:FillValue xsi:nil="true"/>
					<xr:Mask/>
					<xr:ChoiceParameters/>
				</xr:StandardAttribute>
				<xr:StandardAttribute name="Recorder">
					<xr:LinkByType/>
					<xr:FillChecking>DontCheck</xr:FillChecking>
					<xr:MultiLine>false</xr:MultiLine>
					<xr:FillFromFillingValue>false</xr:FillFromFillingValue>
					<xr:CreateOnInput>Auto</xr:CreateOnInput>
					<xr:MaxValue xsi:nil="true"/>
					<xr:ToolTip/>
					<xr:ExtendedEdit>false</xr:ExtendedEdit>
					<xr:Format/>
					<xr:ChoiceForm/>
					<xr:QuickChoice>Auto</xr:QuickChoice>
					<xr:ChoiceHistoryOnInput>Auto</xr:ChoiceHistoryOnInput>
					<xr:EditFormat/>
					<xr:PasswordMode>false</xr:PasswordMode>
					<xr:MarkNegatives>false</xr:MarkNegatives>
					<xr:MinValue xsi:nil="true"/>
					<xr:Synonym/>
					<xr:Comment/>
					<xr:FullTextSearch>Use</xr:FullTextSearch>
					<xr:ChoiceParameterLinks/>
					<xr:FillValue xsi:nil="true"/>
					<xr:Mask/>
					<xr:ChoiceParameters/>
				</xr:StandardAttribute>
				<xr:StandardAttribute name="Period">
					<xr:LinkByType/>
					<xr:FillChecking>ShowError</xr:FillChecking>
					<xr:MultiLine>false</xr:MultiLine>
					<xr:FillFromFillingValue>false</xr:FillFromFillingValue>
					<xr:CreateOnInput>Auto</xr:CreateOnInput>
					<xr:MaxValue xsi:nil="true"/>
					<xr:ToolTip/>
					<xr:ExtendedEdit>false</xr:ExtendedEdit>
					<xr:Format/>
					<xr:ChoiceForm/>
					<xr:QuickChoice>Auto</xr:QuickChoice>
					<xr:ChoiceHistoryOnInput>Auto</xr:ChoiceHistoryOnInput>
					<xr:EditFormat/>
					<xr:PasswordMode>false</xr:PasswordMode>
					<xr:MarkNegatives>false</xr:MarkNegatives>
					<xr:MinValue xsi:nil="true"/>
					<xr:Synonym/>
					<xr:Comment/>
					<xr:FullTextSearch>Use</xr:FullTextSearch>
					<xr:ChoiceParameterLinks/>
					<xr:FillValue xsi:nil="true"/>
					<xr:Mask/>
					<xr:ChoiceParameters/>
				</xr:StandardAttribute>
			</StandardAttributes>
			<InformationRegisterPeriodicity>RecorderPosition</InformationRegisterPeriodicity>
			<WriteMode>RecorderSubordinate</WriteMode>
			<MainFilterOnPeriod>false</MainFilterOnPeriod>
			<IncludeHelpInContents>false</IncludeHelpInContents>
			<DataLockControlMode>Automatic</DataLockControlMode>
			<FullTextSearch>DontUse</FullTextSearch>
			<EnableTotalsSliceFirst>false</EnableTotalsSliceFirst>
			<EnableTotalsSliceLast>false</EnableTotalsSliceLast>
			<RecordPresentation/>
			<ExtendedRecordPresentation/>
			<ListPresentation/>
			<ExtendedListPresentation/>
			<Explanation/>
		</Properties>
		<ChildObjects>
			<Resource uuid="0ce291f9-753b-4b5e-bf3f-ab1d9723eeff">
				<Properties>
					<Name>Цена</Name>
					<Synonym>
						<v8:item>
							<v8:lang>ru</v8:lang>
							<v8:content>Цена</v8:content>
						</v8:item>
						<v8:item>
							<v8:lang>en</v8:lang>
							<v8:content>Price</v8:content>
						</v8:item>
					</Synonym>
					<Comment/>
					<Type>
						<v8:Type>xs:decimal</v8:Type>
						<v8:NumberQualifiers>
							<v8:Digits>15</v8:Digits>
							<v8:FractionDigits>2</v8:FractionDigits>
							<v8:AllowedSign>Any</v8:AllowedSign>
						</v8:NumberQualifiers>
					</Type>
					<PasswordMode>false</PasswordMode>
					<Format/>
					<EditFormat/>
					<ToolTip/>
					<MarkNegatives>false</MarkNegatives>
					<Mask/>
					<MultiLine>false</MultiLine>
					<ExtendedEdit>false</ExtendedEdit>
					<MinValue xsi:nil="true"/>
					<MaxValue xsi:nil="true"/>
					<FillFromFillingValue>false</FillFromFillingValue>
					<FillValue xsi:nil="true"/>
					<FillChecking>DontCheck</FillChecking>
					<ChoiceFoldersAndItems>Items</ChoiceFoldersAndItems>
					<ChoiceParameterLinks/>
					<ChoiceParameters/>
					<QuickChoice>Auto</QuickChoice>
					<CreateOnInput>Auto</CreateOnInput>
					<ChoiceForm/>
					<LinkByType/>
					<ChoiceHistoryOnInput>Auto</ChoiceHistoryOnInput>
					<Indexing>DontIndex</Indexing>
					<FullTextSearch>Use</FullTextSearch>
				</Properties>
			</Resource>
			<Resource uuid="26a94797-9ac4-474f-b0d3-417c0db46156">
				<Properties>
					<Name>ЦенаУпр</Name>
					<Synonym>
						<v8:item>
							<v8:lang>ru</v8:lang>
							<v8:content>Цена упр</v8:content>
						</v8:item>
						<v8:item>
							<v8:lang>en</v8:lang>
							<v8:content>Price</v8:content>
						</v8:item>
					</Synonym>
					<Comment/>
					<Type>
						<v8:Type>xs:decimal</v8:Type>
						<v8:NumberQualifiers>
							<v8:Digits>15</v8:Digits>
							<v8:FractionDigits>2</v8:FractionDigits>
							<v8:AllowedSign>Any</v8:AllowedSign>
						</v8:NumberQualifiers>
					</Type>
					<PasswordMode>false</PasswordMode>
					<Format/>
					<EditFormat/>
					<ToolTip/>
					<MarkNegatives>false</MarkNegatives>
					<Mask/>
					<MultiLine>false</MultiLine>
					<ExtendedEdit>false</ExtendedEdit>
					<MinValue xsi:nil="true"/>
					<MaxValue xsi:nil="true"/>
					<FillFromFillingValue>false</FillFromFillingValue>
					<FillValue xsi:nil="true"/>
					<FillChecking>DontCheck</FillChecking>
					<ChoiceFoldersAndItems>Items</ChoiceFoldersAndItems>
					<ChoiceParameterLinks/>
					<ChoiceParameters/>
					<QuickChoice>Auto</QuickChoice>
					<CreateOnInput>Auto</CreateOnInput>
					<ChoiceForm/>
					<LinkByType/>
					<ChoiceHistoryOnInput>Auto</ChoiceHistoryOnInput>
					<Indexing>DontIndex</Indexing>
					<FullTextSearch>Use</FullTextSearch>
				</Properties>
			</Resource>
			<Attribute uuid="88f3f1c4-cbf8-432a-a9a9-6e571a880cf4">
				<Properties>
					<Name>СтоимостьУслуг</Name>
					<Synonym>
						<v8:item>
							<v8:lang>ru</v8:lang>
							<v8:content>Стоимость услуг</v8:content>
						</v8:item>
						<v8:item>
							<v8:lang>en</v8:lang>
							<v8:content>Cost of services</v8:content>
						</v8:item>
					</Synonym>
					<Comment/>
					<Type>
						<v8:Type>xs:decimal</v8:Type>
						<v8:NumberQualifiers>
							<v8:Digits>15</v8:Digits>
							<v8:FractionDigits>2</v8:FractionDigits>
							<v8:AllowedSign>Any</v8:AllowedSign>
						</v8:NumberQualifiers>
					</Type>
					<PasswordMode>false</PasswordMode>
					<Format/>
					<EditFormat/>
					<ToolTip/>
					<MarkNegatives>false</MarkNegatives>
					<Mask/>
					<MultiLine>false</MultiLine>
					<ExtendedEdit>false</ExtendedEdit>
					<MinValue xsi:nil="true"/>
					<MaxValue xsi:nil="true"/>
					<FillFromFillingValue>false</FillFromFillingValue>
					<FillValue xsi:nil="true"/>
					<FillChecking>DontCheck</FillChecking>
					<ChoiceFoldersAndItems>Items</ChoiceFoldersAndItems>
					<ChoiceParameterLinks/>
					<ChoiceParameters/>
					<QuickChoice>Auto</QuickChoice>
					<CreateOnInput>Auto</CreateOnInput>
					<ChoiceForm/>
					<LinkByType/>
					<ChoiceHistoryOnInput>Auto</ChoiceHistoryOnInput>
					<Indexing>DontIndex</Indexing>
					<FullTextSearch>Use</FullTextSearch>
				</Properties>
			</Attribute>
			<Attribute uuid="ede46aa0-fa8b-4680-96fe-57555cb2c256">
				<Properties>
					<Name>СуммаНДС</Name>
					<Synonym>
						<v8:item>
							<v8:lang>ru</v8:lang>
							<v8:content>Сумма НДС</v8:content>
						</v8:item>
						<v8:item>
							<v8:lang>en</v8:lang>
							<v8:content>Amount of VAT</v8:content>
						</v8:item>
					</Synonym>
					<Comment/>
					<Type>
						<v8:Type>xs:decimal</v8:Type>
						<v8:NumberQualifiers>
							<v8:Digits>15</v8:Digits>
							<v8:FractionDigits>2</v8:FractionDigits>
							<v8:AllowedSign>Any</v8:AllowedSign>
						</v8:NumberQualifiers>
					</Type>
					<PasswordMode>false</PasswordMode>
					<Format/>
					<EditFormat/>
					<ToolTip/>
					<MarkNegatives>false</MarkNegatives>
					<Mask/>
					<MultiLine>false</MultiLine>
					<ExtendedEdit>false</ExtendedEdit>
					<MinValue xsi:nil="true"/>
					<MaxValue xsi:nil="true"/>
					<FillFromFillingValue>false</FillFromFillingValue>
					<FillValue xsi:nil="true"/>
					<FillChecking>DontCheck</FillChecking>
					<ChoiceFoldersAndItems>Items</ChoiceFoldersAndItems>
					<ChoiceParameterLinks/>
					<ChoiceParameters/>
					<QuickChoice>Auto</QuickChoice>
					<CreateOnInput>Auto</CreateOnInput>
					<ChoiceForm/>
					<LinkByType/>
					<ChoiceHistoryOnInput>Auto</ChoiceHistoryOnInput>
					<Indexing>DontIndex</Indexing>
					<FullTextSearch>Use</FullTextSearch>
				</Properties>
			</Attribute>
			<Attribute uuid="ad922a25-69cd-4498-a41c-3aa969e5b153">
				<Properties>
					<Name>СуммаНДСУпр</Name>
					<Synonym>
						<v8:item>
							<v8:lang>ru</v8:lang>
							<v8:content>Сумма НДСУпр</v8:content>
						</v8:item>
						<v8:item>
							<v8:lang>en</v8:lang>
							<v8:content>Amount of VAT</v8:content>
						</v8:item>
					</Synonym>
					<Comment/>
					<Type>
						<v8:Type>xs:decimal</v8:Type>
						<v8:NumberQualifiers>
							<v8:Digits>15</v8:Digits>
							<v8:FractionDigits>2</v8:FractionDigits>
							<v8:AllowedSign>Any</v8:AllowedSign>
						</v8:NumberQualifiers>
					</Type>
					<PasswordMode>false</PasswordMode>
					<Format/>
					<EditFormat/>
					<ToolTip/>
					<MarkNegatives>false</MarkNegatives>
					<Mask/>
					<MultiLine>false</MultiLine>
					<ExtendedEdit>false</ExtendedEdit>
					<MinValue xsi:nil="true"/>
					<MaxValue xsi:nil="true"/>
					<FillFromFillingValue>false</FillFromFillingValue>
					<FillValue xsi:nil="true"/>
					<FillChecking>DontCheck</FillChecking>
					<ChoiceFoldersAndItems>Items</ChoiceFoldersAndItems>
					<ChoiceParameterLinks/>
					<ChoiceParameters/>
					<QuickChoice>Auto</QuickChoice>
					<CreateOnInput>Auto</CreateOnInput>
					<ChoiceForm/>
					<LinkByType/>
					<ChoiceHistoryOnInput>Auto</ChoiceHistoryOnInput>
					<Indexing>DontIndex</Indexing>
					<FullTextSearch>Use</FullTextSearch>
				</Properties>
			</Attribute>
			<Dimension uuid="017c10db-5068-4df6-a095-bf9026e3cf5e">
				<Properties>
					<Name>СтруктурнаяЕдиница</Name>
					<Synonym>
						<v8:item>
							<v8:lang>ru</v8:lang>
							<v8:content>Структурная единица</v8:content>
						</v8:item>
					</Synonym>
					<Comment/>
					<Type>
						<v8:Type>cfg:CatalogRef.СтруктурныеЕдиницы</v8:Type>
					</Type>
					<PasswordMode>false</PasswordMode>
					<Format/>
					<EditFormat/>
					<ToolTip/>
					<MarkNegatives>false</MarkNegatives>
					<Mask/>
					<MultiLine>false</MultiLine>
					<ExtendedEdit>false</ExtendedEdit>
					<MinValue xsi:nil="true"/>
					<MaxValue xsi:nil="true"/>
					<FillFromFillingValue>true</FillFromFillingValue>
					<FillValue xsi:nil="true"/>
					<FillChecking>DontCheck</FillChecking>
					<ChoiceFoldersAndItems>Items</ChoiceFoldersAndItems>
					<ChoiceParameterLinks/>
					<ChoiceParameters/>
					<QuickChoice>Auto</QuickChoice>
					<CreateOnInput>Auto</CreateOnInput>
					<ChoiceForm/>
					<LinkByType/>
					<ChoiceHistoryOnInput>Auto</ChoiceHistoryOnInput>
					<Master>true</Master>
					<MainFilter>true</MainFilter>
					<DenyIncompleteValues>true</DenyIncompleteValues>
					<Indexing>DontIndex</Indexing>
					<FullTextSearch>Use</FullTextSearch>
				</Properties>
			</Dimension>
			<Dimension uuid="ab447a54-a77e-4887-9b2c-534ecdf3b922">
				<Properties>
					<Name>Номенклатура</Name>
					<Synonym>
						<v8:item>
							<v8:lang>ru</v8:lang>
							<v8:content>Номенклатура</v8:content>
						</v8:item>
						<v8:item>
							<v8:lang>en</v8:lang>
							<v8:content>Nomenclature</v8:content>
						</v8:item>
					</Synonym>
					<Comment/>
					<Type>
						<v8:Type>cfg:CatalogRef.Номенклатура</v8:Type>
					</Type>
					<PasswordMode>false</PasswordMode>
					<Format/>
					<EditFormat/>
					<ToolTip/>
					<MarkNegatives>false</MarkNegatives>
					<Mask/>
					<MultiLine>false</MultiLine>
					<ExtendedEdit>false</ExtendedEdit>
					<MinValue xsi:nil="true"/>
					<MaxValue xsi:nil="true"/>
					<FillFromFillingValue>true</FillFromFillingValue>
					<FillValue xsi:nil="true"/>
					<FillChecking>ShowError</FillChecking>
					<ChoiceFoldersAndItems>Items</ChoiceFoldersAndItems>
					<ChoiceParameterLinks/>
					<ChoiceParameters/>
					<QuickChoice>Auto</QuickChoice>
					<CreateOnInput>Auto</CreateOnInput>
					<ChoiceForm/>
					<LinkByType/>
					<ChoiceHistoryOnInput>Auto</ChoiceHistoryOnInput>
					<Master>true</Master>
					<MainFilter>true</MainFilter>
					<DenyIncompleteValues>true</DenyIncompleteValues>
					<Indexing>DontIndex</Indexing>
					<FullTextSearch>Use</FullTextSearch>
				</Properties>
			</Dimension>
			<Dimension uuid="272f8d7a-d13c-4d17-9e1b-e02c4e6f570f">
				<Properties>
					<Name>ЕдиницаИзмерения</Name>
					<Synonym>
						<v8:item>
							<v8:lang>ru</v8:lang>
							<v8:content>Единица измерения</v8:content>
						</v8:item>
						<v8:item>
							<v8:lang>en</v8:lang>
							<v8:content>Measurement unit</v8:content>
						</v8:item>
					</Synonym>
					<Comment/>
					<Type>
						<v8:Type>cfg:CatalogRef.ЕдиницыИзмерения</v8:Type>
					</Type>
					<PasswordMode>false</PasswordMode>
					<Format/>
					<EditFormat/>
					<ToolTip/>
					<MarkNegatives>false</MarkNegatives>
					<Mask/>
					<MultiLine>false</MultiLine>
					<ExtendedEdit>false</ExtendedEdit>
					<MinValue xsi:nil="true"/>
					<MaxValue xsi:nil="true"/>
					<FillFromFillingValue>false</FillFromFillingValue>
					<FillValue xsi:nil="true"/>
					<FillChecking>ShowError</FillChecking>
					<ChoiceFoldersAndItems>Items</ChoiceFoldersAndItems>
					<ChoiceParameterLinks>
						<xr:Link>
							<xr:Name>Отбор.Владелец</xr:Name>
							<xr:DataPath xsi:type="xs:string">InformationRegister.ЦеныНоменклатурыЗакупочные.Dimension.Номенклатура</xr:DataPath>
							<xr:ValueChange>Clear</xr:ValueChange>
						</xr:Link>
					</ChoiceParameterLinks>
					<ChoiceParameters/>
					<QuickChoice>Auto</QuickChoice>
					<CreateOnInput>Auto</CreateOnInput>
					<ChoiceForm/>
					<LinkByType/>
					<ChoiceHistoryOnInput>Auto</ChoiceHistoryOnInput>
					<Master>false</Master>
					<MainFilter>true</MainFilter>
					<DenyIncompleteValues>true</DenyIncompleteValues>
					<Indexing>DontIndex</Indexing>
					<FullTextSearch>Use</FullTextSearch>
				</Properties>
			</Dimension>
			<Dimension uuid="60642647-2feb-491f-b477-40eed961c3a1">
				<Properties>
					<Name>Фирма</Name>
					<Synonym>
						<v8:item>
							<v8:lang>ru</v8:lang>
							<v8:content>Фирма</v8:content>
						</v8:item>
					</Synonym>
					<Comment/>
					<Type>
						<v8:Type>cfg:CatalogRef.Организации</v8:Type>
					</Type>
					<PasswordMode>false</PasswordMode>
					<Format/>
					<EditFormat/>
					<ToolTip/>
					<MarkNegatives>false</MarkNegatives>
					<Mask/>
					<MultiLine>false</MultiLine>
					<ExtendedEdit>false</ExtendedEdit>
					<MinValue xsi:nil="true"/>
					<MaxValue xsi:nil="true"/>
					<FillFromFillingValue>false</FillFromFillingValue>
					<FillValue xsi:nil="true"/>
					<FillChecking>DontCheck</FillChecking>
					<ChoiceFoldersAndItems>Items</ChoiceFoldersAndItems>
					<ChoiceParameterLinks/>
					<ChoiceParameters/>
					<QuickChoice>Auto</QuickChoice>
					<CreateOnInput>Auto</CreateOnInput>
					<ChoiceForm/>
					<LinkByType/>
					<ChoiceHistoryOnInput>Auto</ChoiceHistoryOnInput>
					<Master>false</Master>
					<MainFilter>true</MainFilter>
					<DenyIncompleteValues>true</DenyIncompleteValues>
					<Indexing>Index</Indexing>
					<FullTextSearch>Use</FullTextSearch>
				</Properties>
			</Dimension>
			<Form>ФормаСписка</Form>
		</ChildObjects>
	</InformationRegister>
</MetaDataObject>