<?xml version="1.0" encoding="UTF-8"?>
<Form xmlns="http://v8.1c.ru/8.3/xcf/logform" xmlns:app="http://v8.1c.ru/8.2/managed-application/core" xmlns:cfg="http://v8.1c.ru/8.1/data/enterprise/current-config" xmlns:dcscor="http://v8.1c.ru/8.1/data-composition-system/core" xmlns:dcsset="http://v8.1c.ru/8.1/data-composition-system/settings" xmlns:ent="http://v8.1c.ru/8.1/data/enterprise" xmlns:lf="http://v8.1c.ru/8.2/managed-application/logform" xmlns:style="http://v8.1c.ru/8.1/data/ui/style" xmlns:sys="http://v8.1c.ru/8.1/data/ui/fonts/system" xmlns:v8="http://v8.1c.ru/8.1/data/core" xmlns:v8ui="http://v8.1c.ru/8.1/data/ui" xmlns:web="http://v8.1c.ru/8.1/data/ui/colors/web" xmlns:win="http://v8.1c.ru/8.1/data/ui/colors/windows" xmlns:xr="http://v8.1c.ru/8.3/xcf/readable" xmlns:xs="http://www.w3.org/2001/XMLSchema" xmlns:xsi="http://www.w3.org/2001/XMLSchema-instance">
	<Width>90</Width>
	<VerticalScroll>useIfNecessary</VerticalScroll>
	<AutoCommandBar name="ФормаКоманднаяПанель" id="-1">
		<Autofill>false</Autofill>
	</AutoCommandBar>
	<Events>
		<Event name="OnCreateAtServer">ПриСозданииНаСервере</Event>
	</Events>
	<ChildItems>
		<Table name="Задачи" id="1">
			<AutoInsertNewRow>true</AutoInsertNewRow>
			<EnableStartDrag>true</EnableStartDrag>
			<EnableDrag>true</EnableDrag>
			<DataPath>Объект.Задачи</DataPath>
			<CommandSet>
				<ExcludedCommand>Copy</ExcludedCommand>
				<ExcludedCommand>SortListAsc</ExcludedCommand>
				<ExcludedCommand>MoveUp</ExcludedCommand>
				<ExcludedCommand>CancelSearch</ExcludedCommand>
				<ExcludedCommand>OutputList</ExcludedCommand>
				<ExcludedCommand>SelectAll</ExcludedCommand>
				<ExcludedCommand>SortListDesc</ExcludedCommand>
				<ExcludedCommand>CopyToClipboard</ExcludedCommand>
				<ExcludedCommand>Delete</ExcludedCommand>
				<ExcludedCommand>EndEdit</ExcludedCommand>
				<ExcludedCommand>Add</ExcludedCommand>
				<ExcludedCommand>Change</ExcludedCommand>
				<ExcludedCommand>Find</ExcludedCommand>
				<ExcludedCommand>MoveDown</ExcludedCommand>
			</CommandSet>
			<SearchStringLocation>None</SearchStringLocation>
			<ViewStatusLocation>None</ViewStatusLocation>
			<SearchControlLocation>None</SearchControlLocation>
			<RowFilter xsi:nil="true"/>
			<ContextMenu name="ЗадачиКонтекстноеМеню" id="2"/>
			<AutoCommandBar name="ЗадачиКоманднаяПанель" id="3">
				<Autofill>false</Autofill>
			</AutoCommandBar>
			<ExtendedTooltip name="ЗадачиРасширеннаяПодсказка" id="13"/>
			<SearchStringAddition name="ЗадачиСтрокаПоиска" id="14">
				<Source>
					<lf:elementId>1</lf:elementId>
					<lf:additionId>0</lf:additionId>
				</Source>
				<ContextMenu name="ЗадачиСтрокаПоискаКонтекстноеМеню" id="15"/>
				<ExtendedTooltip name="ЗадачиСтрокаПоискаРасширеннаяПодсказка" id="16"/>
			</SearchStringAddition>
			<ViewStatusAddition name="ЗадачиСостояниеПросмотра" id="17">
				<Source>
					<lf:elementId>1</lf:elementId>
					<lf:additionId>1</lf:additionId>
				</Source>
				<ContextMenu name="ЗадачиСостояниеПросмотраКонтекстноеМеню" id="18"/>
				<ExtendedTooltip name="ЗадачиСостояниеПросмотраРасширеннаяПодсказка" id="19"/>
			</ViewStatusAddition>
			<SearchControlAddition name="ЗадачиУправлениеПоиском" id="20">
				<Source>
					<lf:elementId>1</lf:elementId>
					<lf:additionId>2</lf:additionId>
				</Source>
				<ContextMenu name="ЗадачиУправлениеПоискомКонтекстноеМеню" id="21"/>
				<ExtendedTooltip name="ЗадачиУправлениеПоискомРасширеннаяПодсказка" id="22"/>
			</SearchControlAddition>
			<Events>
				<Event name="Selection">ЗадачиВыбор</Event>
			</Events>
		</Table>
		<Table name="СписокПП" id="23">
			<UseAlternationRowColor>true</UseAlternationRowColor>
			<EnableStartDrag>true</EnableStartDrag>
			<DataPath>СписокПП</DataPath>
			<RowPictureDataPath>СписокПП.DefaultPicture</RowPictureDataPath>
			<AutoRefresh>false</AutoRefresh>
			<AutoRefreshPeriod>60</AutoRefreshPeriod>
			<Period xsi:type="v8:StandardPeriod">
				<v8:variant xsi:type="v8:StandardPeriodVariant">Custom</v8:variant>
				<v8:startDate>0001-01-01T00:00:00</v8:startDate>
				<v8:endDate>0001-01-01T00:00:00</v8:endDate>
			</Period>
			<ChoiceFoldersAndItems>Items</ChoiceFoldersAndItems>
			<RestoreCurrentRow>false</RestoreCurrentRow>
			<TopLevelParent xsi:nil="true"/>
			<ShowRoot>true</ShowRoot>
			<AllowRootChoice>false</AllowRootChoice>
			<UpdateOnDataChange>Auto</UpdateOnDataChange>
			<ContextMenu name="СписокППКонтекстноеМеню" id="24"/>
			<AutoCommandBar name="СписокППКоманднаяПанель" id="25">
				<Autofill>false</Autofill>
			</AutoCommandBar>
			<ExtendedTooltip name="СписокППРасширеннаяПодсказка" id="26"/>
			<SearchStringAddition name="СписокППСтрокаПоиска" id="27">
				<Source>
					<lf:elementId>23</lf:elementId>
					<lf:additionId>0</lf:additionId>
				</Source>
				<ContextMenu name="СписокППСтрокаПоискаКонтекстноеМеню" id="30"/>
				<ExtendedTooltip name="СписокППСтрокаПоискаРасширеннаяПодсказка" id="31"/>
			</SearchStringAddition>
			<ViewStatusAddition name="СписокППСостояниеПросмотра" id="32">
				<Source>
					<lf:elementId>23</lf:elementId>
					<lf:additionId>1</lf:additionId>
				</Source>
				<ContextMenu name="СписокППСостояниеПросмотраКонтекстноеМеню" id="35"/>
				<ExtendedTooltip name="СписокППСостояниеПросмотраРасширеннаяПодсказка" id="36"/>
			</ViewStatusAddition>
			<SearchControlAddition name="СписокППУправлениеПоиском" id="37">
				<Source>
					<lf:elementId>23</lf:elementId>
					<lf:additionId>2</lf:additionId>
				</Source>
				<ContextMenu name="СписокППУправлениеПоискомКонтекстноеМеню" id="40"/>
				<ExtendedTooltip name="СписокППУправлениеПоискомРасширеннаяПодсказка" id="41"/>
			</SearchControlAddition>
			<Events>
				<Event name="Selection">СписокППВыбор</Event>
			</Events>
			<ChildItems>
				<InputField name="СписокПППланируемаяПоставка" id="42">
					<DataPath>СписокПП.ПланируемаяПоставка</DataPath>
					<ContextMenu name="СписокПППланируемаяПоставкаКонтекстноеМеню" id="43"/>
					<ExtendedTooltip name="СписокПППланируемаяПоставкаРасширеннаяПодсказка" id="44"/>
				</InputField>
			</ChildItems>
		</Table>
	</ChildItems>
	<Attributes>
		<Attribute name="Объект" id="1">
			<Type>
				<v8:Type>cfg:DataProcessorObject.Izh_ПриемкаТоваров</v8:Type>
			</Type>
			<MainAttribute>true</MainAttribute>
		</Attribute>
		<Attribute name="СписокПП" id="2">
			<Title>
				<v8:item>
					<v8:lang>ru</v8:lang>
					<v8:content>Список ПП</v8:content>
				</v8:item>
			</Title>
			<Type>
				<v8:Type>cfg:DynamicList</v8:Type>
			</Type>
			<Settings xsi:type="DynamicList">
				<ManualQuery>true</ManualQuery>
				<DynamicDataRead>true</DynamicDataRead>
				<QueryText>ВЫБРАТЬ
	ПланируемаяПоставка.Ссылка КАК ПланируемаяПоставка,
	ПриходнаяНакладная.Ссылка КАК ПН,
	ЗакрытиеЗаказа.Ссылка КАК ЗЗ
ИЗ
	Документ.ПланируемаяПоставка КАК ПланируемаяПоставка
		ЛЕВОЕ СОЕДИНЕНИЕ Документ.ЗакрытиеЗаказа КАК ЗакрытиеЗаказа
		ПО (ЗакрытиеЗаказа.Проведен)
			И ПланируемаяПоставка.Ссылка = ЗакрытиеЗаказа.ДокОснование
		ЛЕВОЕ СОЕДИНЕНИЕ Документ.ПриходнаяНакладная КАК ПриходнаяНакладная
		ПО ПланируемаяПоставка.Ссылка = ПриходнаяНакладная.ДокОснование
			И (НЕ ПриходнаяНакладная.ПометкаУдаления)
ГДЕ
	ПланируемаяПоставка.Контрагент = &amp;Контрагент
	И ПланируемаяПоставка.Проведен
	И ПриходнаяНакладная.Ссылка ЕСТЬ NULL 
	И ЗакрытиеЗаказа.Ссылка ЕСТЬ NULL </QueryText>
				<MainTable>Document.ПланируемаяПоставка</MainTable>
				<ListSettings>
					<dcsset:filter>
						<dcsset:viewMode>Normal</dcsset:viewMode>
						<dcsset:userSettingID>dfcece9d-5077-440b-b6b3-45a5cb4538eb</dcsset:userSettingID>
					</dcsset:filter>
					<dcsset:order>
						<dcsset:viewMode>Normal</dcsset:viewMode>
						<dcsset:userSettingID>88619765-ccb3-46c6-ac52-38e9c992ebd4</dcsset:userSettingID>
					</dcsset:order>
					<dcsset:conditionalAppearance>
						<dcsset:viewMode>Normal</dcsset:viewMode>
						<dcsset:userSettingID>b75fecce-942b-4aed-abc9-e6a02e460fb3</dcsset:userSettingID>
					</dcsset:conditionalAppearance>
					<dcsset:itemsViewMode>Normal</dcsset:itemsViewMode>
					<dcsset:itemsUserSettingID>911b6018-f537-43e8-a417-da56b22f9aec</dcsset:itemsUserSettingID>
				</ListSettings>
			</Settings>
		</Attribute>
	</Attributes>
</Form>