<?xml version="1.0" encoding="UTF-8"?>
<MetaDataObject xmlns="http://v8.1c.ru/8.3/MDClasses" xmlns:app="http://v8.1c.ru/8.2/managed-application/core" xmlns:cfg="http://v8.1c.ru/8.1/data/enterprise/current-config" xmlns:cmi="http://v8.1c.ru/8.2/managed-application/cmi" xmlns:ent="http://v8.1c.ru/8.1/data/enterprise" xmlns:lf="http://v8.1c.ru/8.2/managed-application/logform" xmlns:style="http://v8.1c.ru/8.1/data/ui/style" xmlns:sys="http://v8.1c.ru/8.1/data/ui/fonts/system" xmlns:v8="http://v8.1c.ru/8.1/data/core" xmlns:v8ui="http://v8.1c.ru/8.1/data/ui" xmlns:web="http://v8.1c.ru/8.1/data/ui/colors/web" xmlns:win="http://v8.1c.ru/8.1/data/ui/colors/windows" xmlns:xen="http://v8.1c.ru/8.3/xcf/enums" xmlns:xpr="http://v8.1c.ru/8.3/xcf/predef" xmlns:xr="http://v8.1c.ru/8.3/xcf/readable" xmlns:xs="http://www.w3.org/2001/XMLSchema" xmlns:xsi="http://www.w3.org/2001/XMLSchema-instance">
	<Report uuid="1e432550-39c4-4fc6-9efb-5d78ba230c2e">
		<InternalInfo>
			<xr:GeneratedType name="ReportObject.РасходСпеций" category="Object">
				<xr:TypeId>b7435f6f-c59f-4b87-96ef-3f17247230e5</xr:TypeId>
				<xr:ValueId>b80356db-d870-4228-9136-bf57114d1b50</xr:ValueId>
			</xr:GeneratedType>
			<xr:GeneratedType name="ReportManager.РасходСпеций" category="Manager">
				<xr:TypeId>45aa129e-487b-4fc1-b02e-f62c5dcfa5ff</xr:TypeId>
				<xr:ValueId>0d076cef-d5cb-4f27-88ea-85dd56f944f8</xr:ValueId>
			</xr:GeneratedType>
		</InternalInfo>
		<Properties>
			<Name>РасходСпеций</Name>
			<Synonym>
				<v8:item>
					<v8:lang>ru</v8:lang>
					<v8:content>Расход специй</v8:content>
				</v8:item>
			</Synonym>
			<Comment/>
			<UseStandardCommands>true</UseStandardCommands>
			<DefaultForm/>
			<AuxiliaryForm/>
			<MainDataCompositionSchema/>
			<DefaultSettingsForm/>
			<AuxiliarySettingsForm/>
			<DefaultVariantForm/>
			<VariantsStorage/>
			<SettingsStorage/>
			<IncludeHelpInContents>false</IncludeHelpInContents>
			<ExtendedPresentation/>
			<Explanation/>
		</Properties>
		<ChildObjects>
			<Template>ОП13</Template>
		</ChildObjects>
	</Report>
</MetaDataObject>